.coveragerc
.flake8
.isort.cfg
.pylintrc
.travis.yml
.yapf
AUTHORS
ChangeLog
LICENSE
Makefile
Pipfile
Pipfile.lock
README.rst
development.txt
requirements.txt
setup.cfg
setup.py
samsung_multiroom/__init__.py
samsung_multiroom/base.py
samsung_multiroom/discovery.py
samsung_multiroom/factory.py
samsung_multiroom/group.py
samsung_multiroom/speaker.py
samsung_multiroom.egg-info/PKG-INFO
samsung_multiroom.egg-info/SOURCES.txt
samsung_multiroom.egg-info/dependency_links.txt
samsung_multiroom.egg-info/not-zip-safe
samsung_multiroom.egg-info/pbr.json
samsung_multiroom.egg-info/requires.txt
samsung_multiroom.egg-info/top_level.txt
samsung_multiroom/api/__init__.py
samsung_multiroom/api/api.py
samsung_multiroom/api/api_response.py
samsung_multiroom/api/api_stream.py
samsung_multiroom/clock/__init__.py
samsung_multiroom/clock/alarm.py
samsung_multiroom/clock/clock.py
samsung_multiroom/clock/group.py
samsung_multiroom/clock/timer.py
samsung_multiroom/equalizer/__init__.py
samsung_multiroom/equalizer/equalizer.py
samsung_multiroom/equalizer/group.py
samsung_multiroom/event/__init__.py
samsung_multiroom/event/event.py
samsung_multiroom/event/event_loop.py
samsung_multiroom/event/type/__init__.py
samsung_multiroom/event/type/speaker_mute_changed.py
samsung_multiroom/event/type/speaker_player.py
samsung_multiroom/event/type/speaker_player_repeat_changed.py
samsung_multiroom/event/type/speaker_player_shuffle_changed.py
samsung_multiroom/event/type/speaker_service.py
samsung_multiroom/event/type/speaker_volume_changed.py
samsung_multiroom/service/__init__.py
samsung_multiroom/service/browser.py
samsung_multiroom/service/player.py
samsung_multiroom/service/player_operator.py
samsung_multiroom/service/service.py
samsung_multiroom/service/service_registry.py
samsung_multiroom/service/app/__init__.py
samsung_multiroom/service/app/browser.py
samsung_multiroom/service/app/player.py
samsung_multiroom/service/app/service.py
samsung_multiroom/service/dlna/__init__.py
samsung_multiroom/service/dlna/browser.py
samsung_multiroom/service/dlna/player.py
samsung_multiroom/service/dlna/service.py
samsung_multiroom/service/tunein/__init__.py
samsung_multiroom/service/tunein/browser.py
samsung_multiroom/service/tunein/player.py
samsung_multiroom/service/tunein/service.py
