Metadata-Version: 1.1
Name: samsung-multiroom
Version: 0.0.7
Summary: Samsung multiroom speaker support
Home-page: https://github.com/krygal/samsung_multiroom
Author: Krystian Galutowski
Author-email: k.galutowski@gmail.com
License: MIT
Platform: UNKNOWN
Classifier: Intended Audience :: Information Technology
Classifier: Intended Audience :: System Administrators
Classifier: License :: OSI Approved :: MIT License
Classifier: Operating System :: POSIX :: Linux
Classifier: Programming Language :: Python
Classifier: Programming Language :: Python :: 3
Classifier: Programming Language :: Python :: 3.6
Classifier: Topic :: Home Automation
